LICENSE
MANIFEST.in
README.rst
ez_setup.py
setup.py
import_utils/__init__.py
import_utils.egg-info/PKG-INFO
import_utils.egg-info/SOURCES.txt
import_utils.egg-info/dependency_links.txt
import_utils.egg-info/top_level.txt