Metadata-Version: 1.0
Name: import-utils
Version: 0.0.1
Summary: A module that supports simple programmatic module imports
Home-page: http://askbot.org
Author: Evgeny.Fadeev
Author-email: evgeny.fadeev@gmail.com
License: BSD
Keywords: import,module
Platform: UNKNOWN
Classifier: Development Status :: 4 - Beta
Classifier: Intended Audience :: Developers
Classifier: License :: OSI Approved :: BSD License
Classifier: Operating System :: OS Independent
Classifier: Programming Language :: Python :: 2.5
Classifier: Programming Language :: Python :: 2.6
Classifier: Programming Language :: Python :: 2.7
